scripts.py
liblet/__init__.py
liblet/antlr.py
liblet/automaton.py
liblet/const.py
liblet/decorators.py
liblet/display.py
liblet/grammar.py
liblet/llvm.py
liblet/utils.py
liblet-1.13.2.dist-info/METADATA
liblet-1.13.2.dist-info/WHEEL
liblet-1.13.2.dist-info/entry_points.txt
liblet-1.13.2.dist-info/licenses/LICENSE-CC.txt
liblet-1.13.2.dist-info/licenses/LICENSE-GPL.txt
liblet-1.13.2.dist-info/RECORD
