Metadata-Version: 2.4
Name: liblet
Version: 1.13.2
Summary: A teaching aid library for formal languages and compiler courses.
Project-URL: Documentation, https://liblet.readthedocs.io/
Project-URL: Source code, https://github.com/let-unimi/liblet
Project-URL: Changelog, https://github.com/let-unimi/liblet/blob/master/CHANGELOG.txt
Project-URL: Bug Tracker, https://github.com/let-unimi/liblet/issues
Author-email: Massimo Santini <massimo.santini@unimi.it>
License-File: LICENSE-CC.txt
License-File: LICENSE-GPL.txt
Keywords: automata,formal,grammar,graph,language,parser,parsing,tree
Classifier: Development Status :: 3 - Alpha
Classifier: Framework :: IPython
Classifier: Framework :: Jupyter
Classifier: Intended Audience :: Developers
Classifier: Intended Audience :: Education
Classifier: Intended Audience :: Science/Research
Classifier: License :: OSI Approved :: GNU General Public License v3 (GPLv3)
Classifier: Programming Language :: Python :: 3.10
Classifier: Topic :: Education
Classifier: Topic :: Scientific/Engineering :: Visualization
Classifier: Topic :: Software Development :: Compilers
Requires-Python: >=3.10
Requires-Dist: antlr4-python3-runtime==4.13.2
Requires-Dist: graphviz
Requires-Dist: ipywidgets
Requires-Dist: jupyter
Requires-Dist: svgutils
Provides-Extra: docs
Requires-Dist: pallets-sphinx-themes; extra == 'docs'
Requires-Dist: pystache; extra == 'docs'
Requires-Dist: sphinx; extra == 'docs'
